LEGACY.md
LICENSE
MANIFEST.in
README.md
requirements.txt
setup.py
test/test_org.py
test/test_ttl_sqlite.py
test/test_ttlig.py
test/test_vtt.py
texttaglib/__init__.py
texttaglib/__main__.py
texttaglib/__version__.py
texttaglib/elan.py
texttaglib/orgmode.py
texttaglib/sqlite.py
texttaglib/ttlig.py
texttaglib/vtt.py
texttaglib.egg-info/PKG-INFO
texttaglib.egg-info/SOURCES.txt
texttaglib.egg-info/dependency_links.txt
texttaglib.egg-info/top_level.txt
texttaglib/chirptext/__init__.py
texttaglib/chirptext/__version__.py
texttaglib/chirptext/anhxa.py
texttaglib/chirptext/arsenal.py
texttaglib/chirptext/chio.py
texttaglib/chirptext/chirpnet.py
texttaglib/chirptext/cli.py
texttaglib/chirptext/daophay.py
texttaglib/chirptext/deko.py
texttaglib/chirptext/dekoigo.py
texttaglib/chirptext/dekomecab.py
texttaglib/chirptext/leutile.py
texttaglib/chirptext/luke.py
texttaglib/chirptext/sino.py
texttaglib/chirptext/texttaglib.py
texttaglib/chirptext/data/luke/swadesh/1971.txt
texttaglib/chirptext/data/luke/swadesh/ranked.txt
texttaglib/chirptext/data/luke/swadesh/sign.txt
texttaglib/chirptext/data/sino/kangxi.csv
texttaglib/data/__init__.py
texttaglib/data/scripts/init_corpus.sql
texttaglib/puchikarui/__init__.py
texttaglib/puchikarui/__version__.py
texttaglib/puchikarui/puchikarui.py