Metadata-Version: 2.1
Name: texttaglib
Version: 0.1.1
Summary: Python library for managing and annotating text corpuses in different formats (ELAN, TIG, TTL, et cetera)
Home-page: https://github.com/letuananh/texttaglib
Author: Le Tuan Anh
Author-email: tuananh.ke@gmail.com
License: MIT License
Project-URL: Bug Tracker, https://github.com/letuananh/texttaglib/issues
Project-URL: Source Code, https://github.com/letuananh/texttaglib/
Keywords: nlp,annotation,text,corpus,linguistics,ELAN,transcription
Platform: any
Classifier: Programming Language :: Python
Classifier: Development Status :: 5 - Production/Stable
Classifier: License :: OSI Approved :: MIT License
Classifier: Environment :: Plugins
Classifier: Intended Audience :: Education
Classifier: Intended Audience :: Science/Research
Classifier: Intended Audience :: Information Technology
Classifier: Intended Audience :: Developers
Classifier: Operating System :: OS Independent
Classifier: Topic :: Text Processing
Classifier: Topic :: Text Processing :: Linguistic
Classifier: Topic :: Software Development :: Libraries :: Python Modules
